treecorr-5.1.2.dist-info/METADATA
treecorr-5.1.2.dist-info/RECORD
treecorr-5.1.2.dist-info/top_level.txt
treecorr-5.1.2.dist-info/WHEEL
treecorr/kggcorrelation.py
treecorr/nncorrelation.py
treecorr/gggcorrelation.py
treecorr/__init__.py
treecorr/corr3base.py
treecorr/_treecorr.cpython-313-x86_64-linux-gnu.so
treecorr/zzcorrelation.py
treecorr/config.py
treecorr/kvcorrelation.py
treecorr/exec_corr3.py
treecorr/kzcorrelation.py
treecorr/qqcorrelation.py
treecorr/nkkcorrelation.py
treecorr/catalog.py
treecorr/reader.py
treecorr/kqcorrelation.py
treecorr/nnncorrelation.py
treecorr/kkkcorrelation.py
treecorr/ngcorrelation.py
treecorr/nnkcorrelation.py
treecorr/field.py
treecorr/_version.py
treecorr/vvcorrelation.py
treecorr/kkcorrelation.py
treecorr/exec_corr2.py
treecorr/nvcorrelation.py
treecorr/ntcorrelation.py
treecorr/ggcorrelation.py
treecorr/writer.py
treecorr/ktcorrelation.py
treecorr/nngcorrelation.py
treecorr/nqcorrelation.py
treecorr/corr2base.py
treecorr/util.py
treecorr/kgcorrelation.py
treecorr/nggcorrelation.py
treecorr/ttcorrelation.py
treecorr/kkgcorrelation.py
treecorr/nzcorrelation.py
treecorr/nkcorrelation.py
treecorr/include/Metric.h
treecorr/include/Process2.h
treecorr/include/Position.h
treecorr/include/MultipoleScratch.h
treecorr/include/Corr2.h
treecorr/include/Bounds.h
treecorr/include/Split.h
treecorr/include/BinType.h
treecorr/include/Corr3.h
treecorr/include/ProjectHelper.h
treecorr/include/dbg.h
treecorr/include/Process3.h
treecorr/include/Field.h
treecorr/include/Cell.h
treecorr-5.1.2.data/scripts/corr2
treecorr-5.1.2.data/scripts/corr3
treecorr.libs/libgomp-a34b3233.so.1.0.0
