Metadata-Version: 2.4
Name: TreeCorr
Version: 5.1.2
Summary: Python module for computing 2-point correlation functions
Home-page: https://github.com/rmjarvis/TreeCorr
Download-URL: https://github.com/rmjarvis/TreeCorr/releases/tag/v5.1.2.zip
Author: Mike Jarvis
Author-email: michael@jarvis.net
License: BSD License
Requires-Dist: setuptools>=38
Requires-Dist: numpy>=1.17
Requires-Dist: pybind11<3,>=2.2
Requires-Dist: pyyaml
Requires-Dist: LSSTDESC.Coord>=1.1
Dynamic: author
Dynamic: author-email
Dynamic: description
Dynamic: download-url
Dynamic: home-page
Dynamic: license
Dynamic: requires-dist
Dynamic: summary
